labscript/__init__.py
labscript/__version__.py
labscript/base.py
labscript/compiler.py
labscript/constants.py
labscript/core.py
labscript/functions.py
labscript/inputs.py
labscript/labscript.py
labscript/outputs.py
labscript/remote.py
labscript/utils.py
labscript-3.4.0.dist-info/licenses/LICENSE.txt
labscript-3.4.0.dist-info/METADATA
labscript-3.4.0.dist-info/WHEEL
labscript-3.4.0.dist-info/top_level.txt
labscript-3.4.0.dist-info/RECORD
