Metadata-Version: 2.4
Name: labscript
Version: 3.4.0
Summary: The labscript compiler — expressive control of harware-timed experiments
Author-email: The labscript suite community <labscriptsuite@googlegroups.com>
License: Copyright (c) 2013, Monash University
Project-URL: Homepage, http://labscriptsuite.org/
Project-URL: Documentation, https://docs.labscriptsuite.org/
Project-URL: Repository, https://github.com/labscript-suite/labscript/
Project-URL: Downloads, https://github.com/labscript-suite/labscript/releases/
Project-URL: Tracker, https://github.com/labscript-suite/labscript/issues/
Keywords: experiment control,automation
Classifier: License :: OSI Approved :: BSD License
Classifier: Programming Language :: Python :: 3 :: Only
Requires-Python: >=3.8
License-File: LICENSE.txt
Requires-Dist: labscript_utils>=3.0.0
Requires-Dist: numpy>=1.15
Requires-Dist: scipy
Requires-Dist: matplotlib
Provides-Extra: docs
Requires-Dist: PyQt5; extra == "docs"
Requires-Dist: Sphinx==7.2.6; extra == "docs"
Requires-Dist: sphinx-rtd-theme==2.0.0; extra == "docs"
Requires-Dist: myst_parser==2.0.0; extra == "docs"
Dynamic: license-file
